{
  "source_dir": "Dataset/VN30",
  "benchmark": "VN30",
  "raw_panel_path": "Dataset/vn30_panel_raw.csv",
  "feature_panel_path": "Dataset/vn30_panel_features.csv",
  "balanced_feature_panel_path": "Dataset/vn30_panel_features_balanced.csv",
  "raw_rows": 63955,
  "feature_rows": 59593,
  "balanced_feature_rows": 30030,
  "num_stock_tickers": 30,
  "stock_tickers": [
    "ACB",
    "BCM",
    "BID",
    "BVH",
    "CTG",
    "FPT",
    "GAS",
    "GVR",
    "HDB",
    "HPG",
    "MBB",
    "MSN",
    "MWG",
    "NVL",
    "PDR",
    "PLX",
    "POW",
    "SAB",
    "SSI",
    "STB",
    "TCB",
    "TPB",
    "VCB",
    "VHM",
    "VIB",
    "VIC",
    "VJC",
    "VNM",
    "VPB",
    "VRE"
  ],
  "date_start": "2013-01-02",
  "date_end": "2023-06-30",
  "feature_columns": [
    "ret_1d",
    "ret_5d",
    "ret_20d",
    "oc_return",
    "hl_range",
    "volume_change_1d",
    "value_change_1d",
    "rolling_vol_5",
    "rolling_vol_20",
    "ma_ratio_5",
    "ma_ratio_20",
    "volume_ma_ratio_5",
    "volume_ma_ratio_20",
    "market_ret_1d",
    "market_ret_5d",
    "market_vol_20",
    "relative_ret_1d"
  ],
  "target_columns": [
    "target_return_1d",
    "target_direction_1d"
  ],
  "recommended_tensor_shape": {
    "X": "(samples, lookback, num_stocks, num_features)",
    "Y": "(samples, num_stocks)"
  },
  "notes": [
    "Rows with Ticker == VN30 are benchmark/index rows and are excluded from stock-node feature panel.",
    "Rolling features use current and past observations only.",
    "target_return_1d is next trading day's log return per stock.",
    "Correlation graphs for experiments should be computed from train dates only.",
    "The balanced feature panel keeps only dates where all 30 stock nodes are present.",
    "Large single-day returns may indicate corporate actions if source prices are not adjusted."
  ],
  "per_ticker_coverage": [
    {
      "Ticker": "ACB",
      "rows": 2619,
      "start": "2013-01-02",
      "end": "2023-06-30"
    },
    {
      "Ticker": "BCM",
      "rows": 1341,
      "start": "2018-02-21",
      "end": "2023-06-30"
    },
    {
      "Ticker": "BID",
      "rows": 2353,
      "start": "2014-01-23",
      "end": "2023-06-30"
    },
    {
      "Ticker": "BVH",
      "rows": 2618,
      "start": "2013-01-02",
      "end": "2023-06-30"
    },
    {
      "Ticker": "CTG",
      "rows": 2618,
      "start": "2013-01-02",
      "end": "2023-06-30"
    },
    {
      "Ticker": "FPT",
      "rows": 2618,
      "start": "2013-01-02",
      "end": "2023-06-30"
    },
    {
      "Ticker": "GAS",
      "rows": 2618,
      "start": "2013-01-02",
      "end": "2023-06-30"
    },
    {
      "Ticker": "GVR",
      "rows": 1320,
      "start": "2018-03-21",
      "end": "2023-06-30"
    },
    {
      "Ticker": "HDB",
      "rows": 1369,
      "start": "2018-01-05",
      "end": "2023-06-30"
    },
    {
      "Ticker": "HPG",
      "rows": 2618,
      "start": "2013-01-02",
      "end": "2023-06-30"
    },
    {
      "Ticker": "MBB",
      "rows": 2618,
      "start": "2013-01-02",
      "end": "2023-06-30"
    },
    {
      "Ticker": "MSN",
      "rows": 2618,
      "start": "2013-01-02",
      "end": "2023-06-30"
    },
    {
      "Ticker": "MWG",
      "rows": 2242,
      "start": "2014-07-14",
      "end": "2023-06-30"
    },
    {
      "Ticker": "NVL",
      "rows": 1625,
      "start": "2016-12-28",
      "end": "2023-06-30"
    },
    {
      "Ticker": "PDR",
      "rows": 2618,
      "start": "2013-01-02",
      "end": "2023-06-30"
    },
    {
      "Ticker": "PLX",
      "rows": 1550,
      "start": "2017-04-21",
      "end": "2023-06-30"
    },
    {
      "Ticker": "POW",
      "rows": 1322,
      "start": "2018-03-06",
      "end": "2023-06-30"
    },
    {
      "Ticker": "SAB",
      "rows": 1641,
      "start": "2016-12-06",
      "end": "2023-06-30"
    },
    {
      "Ticker": "SSI",
      "rows": 2618,
      "start": "2013-01-02",
      "end": "2023-06-30"
    },
    {
      "Ticker": "STB",
      "rows": 2618,
      "start": "2013-01-02",
      "end": "2023-06-30"
    },
    {
      "Ticker": "TCB",
      "rows": 1271,
      "start": "2018-06-04",
      "end": "2023-06-30"
    },
    {
      "Ticker": "TPB",
      "rows": 1298,
      "start": "2018-04-19",
      "end": "2023-06-30"
    },
    {
      "Ticker": "VCB",
      "rows": 2616,
      "start": "2013-01-02",
      "end": "2023-06-30"
    },
    {
      "Ticker": "VHM",
      "rows": 1281,
      "start": "2018-05-17",
      "end": "2023-06-30"
    },
    {
      "Ticker": "VIB",
      "rows": 1616,
      "start": "2017-01-09",
      "end": "2023-06-30"
    },
    {
      "Ticker": "VIC",
      "rows": 2616,
      "start": "2013-01-02",
      "end": "2023-06-30"
    },
    {
      "Ticker": "VJC",
      "rows": 1585,
      "start": "2017-02-28",
      "end": "2023-06-30"
    },
    {
      "Ticker": "VNM",
      "rows": 2616,
      "start": "2013-01-02",
      "end": "2023-06-30"
    },
    {
      "Ticker": "VPB",
      "rows": 1467,
      "start": "2017-08-17",
      "end": "2023-06-30"
    },
    {
      "Ticker": "VRE",
      "rows": 1411,
      "start": "2017-11-06",
      "end": "2023-06-30"
    }
  ]
}